qprof_qiskit/NamedRoutine.py
qprof_qiskit/RoutineWrapper.py
qprof_qiskit/WrappedQuantumCircuit.py
qprof_qiskit/__init__.py
qprof_qiskit/_interfaces.py
qprof_qiskit/name_routines.py
qprof_qiskit/supports_routine_test.py
qprof_qiskit-1.0.1.dist-info/LICENSE
qprof_qiskit-1.0.1.dist-info/METADATA
qprof_qiskit-1.0.1.dist-info/WHEEL
qprof_qiskit-1.0.1.dist-info/top_level.txt
qprof_qiskit-1.0.1.dist-info/RECORD
