Metadata-Version: 2.1
Name: qprof-qiskit
Version: 1.0.1
Summary: qprof plugin for qiskit framework.
Home-page: UNKNOWN
Author: Adrien Suau
Author-email: adrien.suau@cerfacs.fr
License: UNKNOWN
Project-URL: Collaborator, https://cerfacs.fr/en
Keywords: quantum,performance,gprof,profiling,qiskit,plugin
Platform: UNKNOWN
Classifier: Development Status :: 3 - Alpha
Classifier: Intended Audience :: Developers
Classifier: Intended Audience :: Education
Classifier: Intended Audience :: Science/Research
Classifier: Topic :: Scientific/Engineering
Classifier: Topic :: Scientific/Engineering :: Mathematics
Classifier: License :: CeCILL-B Free Software License Agreement (CECILL-B)
Classifier: Natural Language :: English
Classifier: Operating System :: OS Independent
Classifier: Programming Language :: Python :: 3 :: Only
Requires-Dist: qiskit (==0.21.0)
Requires-Dist: qprof
Requires-Dist: qprof-interfaces
Provides-Extra: dev
Requires-Dist: black ; extra == 'dev'
Requires-Dist: pygments ; extra == 'dev'
Requires-Dist: setuptools ; extra == 'dev'
Requires-Dist: wheel ; extra == 'dev'
Requires-Dist: twine ; extra == 'dev'
